pyDocxReport/__init__.py
pyDocxReport/databridge.py
pyDocxReport/docx_template.py
tests/__init__.py
tests/unit/__init__.py
tests/unit/test_databridge.py
pyDocxReport-0.1.0.dist-info/LICENSE
pyDocxReport-0.1.0.dist-info/METADATA
pyDocxReport-0.1.0.dist-info/WHEEL
pyDocxReport-0.1.0.dist-info/top_level.txt
pyDocxReport-0.1.0.dist-info/RECORD
