Metadata-Version: 2.1
Name: pyDocxReport
Version: 0.1.0
Summary: module to ease the docx report generation using templates and importing features
Home-page: https://github.com/20centcroak/pyDocxReport
Author: 20centCroak
Author-email: 
License: UNKNOWN
Platform: UNKNOWN
Classifier: Programming Language :: Python :: 3
Classifier: License :: OSI Approved :: MIT License
Classifier: Operating System :: OS Independent
Requires-Python: >=3.6
License-File: LICENSE
Requires-Dist: pandas
Requires-Dist: python-docx
